{
  "date_input": "Enter the date",
  "from": "From",
  "search_btn": "Search",
  "search_title": "Search for bus tickets online",
  "to": "To",
  "title": "International transportation to Portugal and Lithuania",
  "description": "Order the best tickets for the best flights.",
  "search_results": "Search results:",
  "no_results": "The route does not exist.",
  "routs_card": {
    "number": "Number:",
    "conveniences": "Conveniences:",
    "conveniences_icon": {
      "wifi": {
        "icon": "/wifi.svg",
        "name": "wifi",
        "aria": "wifi"
      },
      "conditioning": {
        "icon": "/air-conditioner.svg",
        "name": "conditioning",
        "aria": "air conditioning"
      },
      "wc": {
        "icon": "/wc.svg",
        "name": "wc",
        "aria": "wc"
      },
      "seats": {
        "icon": "/car-seat.svg",
        "name": "seats",
        "aria": "seats"
      },
      "socket": {
        "icon": "/power.svg",
        "name": "socket",
        "aria": "socket"
      }
    },
    "price": "Price:",
    "routs": "Route:",
    "seat": "Seat",
    "duration": "Duration on the way: ",
    "baggage": {
      "title": "Baggage:",
      "light_luggage": "Light luggage - free for one passenger: 1 piece of hand luggage (max. size 15x25x35 cm)",
      "heavy_luggage": "Heavy luggage - 1 piece of luggage up to 30 kg, size up to 30x60x80 cm in the luggage compartment"
    },
    "cancellation": "Ticket cancellation terms",
    "cancellation_btn": {
      "title": "Cancel",
      "href": "#"
    },
    "cancellation_info": {
      "title": "Ticket cancellation information",
      "text": "Up to 48 hours before departure: 90% From 48 to 24 hours before departure: 80% Less than 24 hours before departure: ticket is non-refundable",
      "href": "/"
    },
    "booking_btn": {
      "title": "Book",
      "href": "#"
    },
    "read_more_btn": {
      "title": "Read more"
    }
  },
  "seat_booking": {
    "title": "Choose a seat",
    "seats": [
       { "name": "occupied", "title": "Occupied" },
      { "name": "available", "title": "Available" },     
      { "name": "selected", "title": "Selected" }
    ],
    "selected_seats": "Selected seats: ",
    "float": "Floor "
  },
  "cancel_btn": {
    "title": "Cancel"
  },
  "select_btn": {
    "title": "Select"
  }
}
